rdkit_dof/__init__.py
rdkit_dof/config.py
rdkit_dof/core.py
rdkit_dof/palettes.py
rdkit_dof-0.1.3.dist-info/METADATA
rdkit_dof-0.1.3.dist-info/WHEEL
rdkit_dof-0.1.3.dist-info/licenses/LICENSE
rdkit_dof-0.1.3.dist-info/RECORD
