Metadata-Version: 2.4
Name: rdkit-dof
Version: 0.1.3
Summary: RDKit molecule drawing with Depth of Field (DOF) effects.
Project-URL: Homepage, https://github.com/gentle1999/rdkit-dof
Project-URL: Bug Tracker, https://github.com/gentle1999/rdkit-dof/issues
Project-URL: Repository, https://github.com/gentle1999/rdkit-dof.git
Author-email: Miao-Jiong Tang <mj_t@zju.edu.cn>
License: MIT
License-File: LICENSE
Keywords: DOF,cheminformatics,chemistry,drawing,molecule,rdkit,visualization
Classifier: Development Status :: 4 - Beta
Classifier: Intended Audience :: Developers
Classifier: Intended Audience :: Science/Research
Classifier: License :: OSI Approved :: MIT License
Classifier: Operating System :: OS Independent
Classifier: Programming Language :: Python :: 3
Classifier: Programming Language :: Python :: 3.9
Classifier: Programming Language :: Python :: 3.10
Classifier: Programming Language :: Python :: 3.11
Classifier: Programming Language :: Python :: 3.12
Classifier: Programming Language :: Python :: 3.13
Classifier: Programming Language :: Python :: 3.14
Classifier: Topic :: Scientific/Engineering :: Chemistry
Classifier: Topic :: Scientific/Engineering :: Visualization
Classifier: Typing :: Typed
Requires-Python: >=3.9
Requires-Dist: pydantic-settings>=2.11.0
Requires-Dist: pydantic>=2.12.5
Requires-Dist: rdkit>=2023.9.6
